pyimport/LICENSE
pyimport/TODO
pyimport/__init__.py
pyimport/api.py
pyimport/argmgr.py
pyimport/argparser.py
pyimport/asyncaudit.py
pyimport/asyncimport.py
pyimport/asynctest.py
pyimport/audit.py
pyimport/batchid.py
pyimport/canonical_path.py
pyimport/compounddateformats.py
pyimport/convertdelimiter.py
pyimport/counter.py
pyimport/csvreader.py
pyimport/dateformats.py
pyimport/db/__init__.py
pyimport/db/asyncdbwriter.py
pyimport/db/asyncinserter.py
pyimport/db/asyncrdbwriter.py
pyimport/db/dbwriter.py
pyimport/db/postgresuri.py
pyimport/db/rdbmaker.py
pyimport/db/rdbmanager.py
pyimport/db/rdbwriter.py
pyimport/db/syncmdbwriter.py
pyimport/db/syncrdbwriter.py
pyimport/doctimestamp.py
pyimport/dropcommand.py
pyimport/enricher.py
pyimport/fieldfile.py
pyimport/filereader.py
pyimport/filesplitter.py
pyimport/generatefieldfilecommand.py
pyimport/guessdatetimeformat.py
pyimport/importcmd.py
pyimport/importresult.py
pyimport/liner.py
pyimport/liner.txt
pyimport/linerdoseol.txt
pyimport/linereader.py
pyimport/logger.py
pyimport/makemdbfieldfile.py
pyimport/mdbimportcmd.py
pyimport/memoize.py
pyimport/mongimportgen.py
pyimport/monotonicid.py
pyimport/multiimportcommand.py
pyimport/nested_builder.py
pyimport/parallellimportcommand.py
pyimport/pwc.py
pyimport/pyimport_main.py
pyimport/rdbimport.py
pyimport/rest_api.py
pyimport/splitfile.py
pyimport/threadimportcommand.py
pyimport/timer.py
pyimport/type_converter.py
pyimport/updatestackoverflow.py
pyimport/version.py
pyimport-2.0.7.dist-info/LICENSE
pyimport-2.0.7.dist-info/METADATA
pyimport-2.0.7.dist-info/WHEEL
pyimport-2.0.7.dist-info/entry_points.txt
pyimport-2.0.7.dist-info/RECORD
