Metadata-Version: 2.3
Name: pyimport
Version: 2.0.7
Summary: A CSV importer for MongoDB
License: Apache-2.0
Author: Joe Drumgoole
Requires-Python: >=3.10,<4.0
Classifier: License :: OSI Approved :: Apache Software License
Classifier: Programming Language :: Python :: 3
Classifier: Programming Language :: Python :: 3.10
Classifier: Programming Language :: Python :: 3.11
Classifier: Programming Language :: Python :: 3.12
Classifier: Programming Language :: Python :: 3.13
Provides-Extra: rest-api
Requires-Dist: aiocsv (>=1.3.2,<2.0.0)
Requires-Dist: aiofile (>=3.8.8,<4.0.0)
Requires-Dist: aiofiles (>=23.2.1,<24.0.0)
Requires-Dist: aiohttp (>=3.9.5,<4.0.0)
Requires-Dist: asyncstdlib (>=3.12.3,<4.0.0)
Requires-Dist: colorama (>=0.4.6,<0.5.0)
Requires-Dist: configargparse (>=1.7,<2.0)
Requires-Dist: dnspython (>=2.6.1,<3.0.0)
Requires-Dist: fastapi (>=0.115.0,<0.116.0) ; extra == "rest-api"
Requires-Dist: motor (>=3.4.0,<4.0.0)
Requires-Dist: psycopg (>=3.2.1,<4.0.0)
Requires-Dist: psycopg2-binary (>=2.9.9,<3.0.0)
Requires-Dist: py-dateinfer (>=0.4.5,<0.5.0)
Requires-Dist: pymongo (>=4.7.3,<5.0.0)
Requires-Dist: python-dateutil (>=2.9.0.post0,<3.0.0)
Requires-Dist: pytz (>=2024.1,<2025.0)
Requires-Dist: requests (>=2.32.2,<3.0.0)
Requires-Dist: sqlalchemy (>=2.0.34,<3.0.0)
Requires-Dist: toml (>=0.10.2,<0.11.0)
Requires-Dist: tqdm (>=4.66.4,<5.0.0)
Requires-Dist: uvicorn (>=0.32.0,<0.33.0) ; extra == "rest-api"
